[
  {
    "collection": "werkvergunningens",
    "fields": [
      "sblNumber",
      "datum",
      "workType",
      "cables",
      "straat",
      "huisnummer",
      "postcode",
      "gemeente",
      "ploegLeden",
      "plaats",
      "opgemaaktOp",
      "werkverantwoordelijkeNaam",
      "werkverantwoordelijkeVoornaam",
      "werkverantwoordelijkeHoedanigheid",
      "werkverantwoordelijkeAannemer",
      "werkverantwoordelijkeHandtekening",
      "schakelbevoegdeNaam",
      "schakelbevoegdeVoornaam",
      "schakelbevoegdeHandtekening",
      "photos",
      "recipientEmail",
      "emailStatus"
    ],
    "generator": "crouton-cli",
    "timestamp": "2026-04-23T16:08:48.145Z",
    "layer": "kvr",
    "gitSha": "20540025"
  },
  {
    "collection": "settings",
    "fields": [
      "recipients"
    ],
    "generator": "crouton-cli",
    "timestamp": "2026-04-23T16:08:48.124Z",
    "layer": "kvr",
    "gitSha": "20540025"
  },
  {
    "collection": "werkvergunningens",
    "fields": [
      "sblNumber",
      "datum",
      "workType",
      "cables",
      "straat",
      "huisnummer",
      "postcode",
      "gemeente",
      "ploegLeden",
      "plaats",
      "opgemaaktOp",
      "werkverantwoordelijkeNaam",
      "werkverantwoordelijkeVoornaam",
      "werkverantwoordelijkeHoedanigheid",
      "werkverantwoordelijkeAannemer",
      "werkverantwoordelijkeHandtekening",
      "schakelbevoegdeNaam",
      "schakelbevoegdeVoornaam",
      "schakelbevoegdeHandtekening",
      "photos",
      "recipientEmail",
      "emailStatus"
    ],
    "generator": "crouton-cli",
    "timestamp": "2026-04-23T15:55:50.504Z",
    "layer": "kvr",
    "gitSha": "20540025"
  },
  {
    "collection": "settings",
    "fields": [
      "recipients"
    ],
    "generator": "crouton-cli",
    "timestamp": "2026-04-23T15:55:50.472Z",
    "layer": "kvr",
    "gitSha": "20540025"
  }
]